FourierAnim.py
__init__.py
FourierAnim-1.1.2.dist-info/LICENSE
FourierAnim-1.1.2.dist-info/METADATA
FourierAnim-1.1.2.dist-info/WHEEL
FourierAnim-1.1.2.dist-info/top_level.txt
FourierAnim-1.1.2.dist-info/RECORD
