Metadata-Version: 2.1
Name: FourierAnim
Version: 1.1.2
Summary: An animation tool to create visualisations for Fourier Series on top of manimCE
Author-email: Shaheer Ziya <shaheer@connect.hku.hk>
License: MIT License
Project-URL: Homepage, https://github.com/MatthewSummons/FourierAnim.git
Keywords: math,animation,fourier
Classifier: License :: OSI Approved :: MIT License
Classifier: Programming Language :: Python
Classifier: Programming Language :: Python :: 3
Requires-Python: >=3.10
License-File: LICENSE
Requires-Dist: manim >=0.18.0
